{
    "id": "ethereum",
    "symbol": "eth",
    "name": "Ethereum",
    "localization": {
        "en": "Ethereum",
        "de": "Ethereum",
        "es": "Ethereum",
        "fr": "Ethereum",
        "it": "Ethereum",
        "pl": "Ethereum",
        "ro": "Ethereum",
        "hu": "Ethereum",
        "nl": "Ethereum",
        "pt": "Ethereum",
        "sv": "Ethereum",
        "vi": "Ethereum",
        "tr": "Ethereum",
        "ru": "Эфириум",
        "ja": "イーサリアム",
        "zh": "以太坊",
        "zh-tw": "以太幣",
        "ko": "이더리움",
        "ar": "يثريوم",
        "th": "Ethereum",
        "id": "Ethereum",
        "cs": "Ethereum",
        "da": "Ethereum",
        "el": "Ethereum",
        "hi": "Ethereum",
        "no": "Ethereum",
        "sk": "Ethereum",
        "uk": "Ethereum",
        "he": "Ethereum",
        "fi": "Ethereum",
        "bg": "Ethereum",
        "hr": "Ethereum",
        "lt": "Ethereum",
        "sl": "Ethereum"
    },
    "image": {
        "thumb": "https://assets.coingecko.com/coins/images/279/thumb/ethereum.png?1595348880",
        "small": "https://assets.coingecko.com/coins/images/279/small/ethereum.png?1595348880"
    },
    "market_data": {
        "current_price": {
            "aed": 6313.492075906015,
            "ars": 356587.6924786628,
            "aud": 2581.905980234231,
            "bch": 14.273807546488902,
            "bdt": 180599.12385669435,
            "bhd": 648.2787437440196,
            "bmd": 1719.1709726748606,
            "bnb": 5.518462469750675,
            "brl": 8937.626052742035,
            "btc": 0.06321791762421583,
            "cad": 2347.6826885750593,
            "chf": 1573.3302607209057,
            "clp": 1386047.2132996537,
            "cny": 11836.921939609589,
            "czk": 37850.89790849177,
            "dkk": 11854.19960788493,
            "dot": 292.2343206981916,
            "eos": 1578.8194500878933,
            "eth": 1.0,
            "eur": 1590.8812771809432,
            "gbp": 1398.2086287603543,
            "hkd": 13494.984980060712,
            "huf": 614221.5008799948,
            "idr": 25977798.022034828,
            "ils": 6173.508579455964,
            "inr": 141342.92917752225,
            "jpy": 225653.43925675566,
            "krw": 2231784.7774521853,
            "kwd": 526.7196026081228,
            "lkr": 558549.9689278208,
            "ltc": 19.224212866487225,
            "mmk": 3608828.2539793383,
            "mxn": 31514.766070046597,
            "myr": 7599.595284709229,
            "ngn": 792091.6969740451,
            "nok": 17987.7598114489,
            "nzd": 2771.9070369632814,
            "php": 92989.9647886667,
            "pkr": 487264.71474378393,
            "pln": 7458.587162359419,
            "rub": 131535.65189239738,
            "sar": 6456.489279071165,
            "sek": 17828.17260839744,
            "sgd": 2287.704251680378,
            "thb": 59156.67316974186,
            "try": 32829.21325067629,
            "twd": 52233.5716627802,
            "uah": 63465.864609641794,
            "usd": 1719.1709726748606,
            "vef": 172.1405894939334,
            "vnd": 40426810.169327736,
            "xag": 74.39930718963971,
            "xau": 0.8781869162617707,
            "xdr": 1280.8786482172388,
            "xlm": 18523.214794251362,
            "xrp": 3578.134161419662,
            "yfi": 0.21189960216760378,
            "zar": 31474.23833353676,
            "bits": 63217.917624215836,
            "link": 249.55208320199569,
            "sats": 6321791.762421583
        },
        "market_cap": {
            "aed": 759031359192.0381,
            "ars": 42870663808877.66,
            "aud": 310428811271.1558,
            "bch": 1720180283.407339,
            "bdt": 21712294369224.61,
            "bhd": 77938467346.3322,
            "bmd": 206685090340.53693,
            "bnb": 664850258.9335442,
            "brl": 1074473110644.3134,
            "btc": 7608526.458100925,
            "cad": 282243992241.7781,
            "chf": 189168528934.17618,
            "clp": 166635720385251.06,
            "cny": 1423078518267.1775,
            "czk": 4550564965518.56,
            "dkk": 1425057528007.1938,
            "dot": 35187356466.52993,
            "eos": 190345607076.45987,
            "eth": 120452174.606695,
            "eur": 191233106301.58768,
            "gbp": 168109178394.28833,
            "hkd": 1622415953646.1116,
            "huf": 73842004405618.38,
            "idr": 3123486252851933,
            "ils": 742202025711.0599,
            "inr": 16992623796491.215,
            "jpy": 27130828411186.082,
            "krw": 268313417152825.8,
            "kwd": 63324177978.53357,
            "lkr": 67150942298619.195,
            "ltc": 2316043055.1074924,
            "mmk": 433866675015265.75,
            "mxn": 3788785728050.441,
            "myr": 913651441850.3442,
            "ngn": 95228192279414.39,
            "nok": 2162324947186.37,
            "nzd": 333363208950.61255,
            "php": 11179597363260.016,
            "pkr": 58580765489472.78,
            "pln": 896706364718.7705,
            "rub": 15813702375443.312,
            "sar": 776223011636.3833,
            "sek": 2143324386831.3674,
            "sgd": 275035849716.1523,
            "thb": 7114927549882.633,
            "try": 3946849390998.9136,
            "twd": 6279713099816.526,
            "uah": 7630100885181.149,
            "usd": 206685090340.53693,
            "vef": 20695378095.797966,
            "vnd": 4860260581893555,
            "xag": 8943205987.209755,
            "xau": 105580944.69865598,
            "xdr": 153991966668.75876,
            "xlm": 2232539611325.952,
            "xrp": 429205802006.83673,
            "yfi": 25545501.58903348,
            "zar": 3784052639481.6416,
            "bits": 7608526458100.926,
            "link": 30062191436.32184,
            "sats": 760852645810092.5
        },
        "total_volume": {
            "aed": 35833180507.713844,
            "ars": 2023867456835.831,
            "aud": 14653998441.964037,
            "bch": 81013156.61702254,
            "bdt": 1025017680688.7361,
            "bhd": 3679404197.329229,
            "bmd": 9757415238.165146,
            "bnb": 31320869.564129937,
            "brl": 50726850340.17279,
            "btc": 358802.8663558953,
            "cad": 13324628675.085922,
            "chf": 8929674188.681114,
            "clp": 7866720887465.892,
            "cny": 67182243268.57661,
            "czk": 214828503913.0893,
            "dkk": 67280305291.719925,
            "dot": 1658620148.442128,
            "eos": 8960828914.316858,
            "eth": 5675682.873984069,
            "eur": 9029287640.847542,
            "gbp": 7935744842.860662,
            "hkd": 76592831182.10112,
            "huf": 3486107157201.6353,
            "idr": 147440927227729.47,
            "ils": 35038682971.946236,
            "inr": 802213202109.7612,
            "jpy": 1280730271592.7468,
            "krw": 12666832526805.03,
            "kwd": 2989476880.669032,
            "lkr": 3170134945690.3164,
            "ltc": 109109931.79075089,
            "mmk": 20482451342527.74,
            "mxn": 178866828004.10406,
            "myr": 43132654060.30908,
            "ngn": 4495636395054.668,
            "nok": 102092255205.77722,
            "nzd": 15732378216.670795,
            "php": 527778629262.0114,
            "pkr": 2765544688823.9067,
            "pln": 42332341105.05928,
            "rub": 746550514484.284,
            "sar": 36644782792.39394,
            "sek": 101186493864.04883,
            "sgd": 12984211972.256811,
            "thb": 335752658345.26215,
            "try": 186327172061.73083,
            "twd": 296459547181.1712,
            "uah": 360210127025.31445,
            "usd": 9757415238.165146,
            "vef": 977009987.7974739,
            "vnd": 229448484092809.84,
            "xag": 422264536.3489482,
            "xau": 4984282.851959511,
            "xdr": 7269820767.686359,
            "xlm": 105131311059.78523,
            "xrp": 20308242371.32957,
            "yfi": 1202668.286060193,
            "zar": 178636806697.27957,
            "bits": 358802866355.8953,
            "link": 1416370644.952442,
            "sats": 35880286635589.53
        }
    },
    "community_data": {
        "facebook_likes": null,
        "twitter_followers": null,
        "reddit_average_posts_48h": 0.0,
        "reddit_average_comments_48h": 0.0,
        "reddit_subscribers": null,
        "reddit_accounts_active_48h": null
    },
    "developer_data": {
        "forks": null,
        "stars": null,
        "subscribers": null,
        "total_issues": null,
        "closed_issues": null,
        "pull_requests_merged": null,
        "pull_request_contributors": null,
        "code_additions_deletions_4_weeks": {
            "additions": null,
            "deletions": null
        },
        "commit_count_4_weeks": null
    },
    "public_interest_stats": {
        "alexa_rank": null,
        "bing_matches": null
    }
}
